[
  {
    "id": 1,
    "name": "미션테스트",
    "missionDetailResponseList": [
      {
        "id": 1,
        "name": "takeoff",
        "index": 1,
        "mapX": 0.0,
        "mapY": 0.0,
        "mapZ": 100.0,
        "speed": 0.0,
        "time": 0.0
      },
      {
        "id": 2,
        "name": "waypoint",
        "index": 2,
        "mapX": 3.744568E8,
        "mapY": 1.26891725E9,
        "mapZ": 100.0,
        "speed": 0.0,
        "time": 0.0
      },
      {
        "id": 3,
        "name": "waypoint",
        "index": 3,
        "mapX": 3.7443536E8,
        "mapY": 1.26893184E9,
        "mapZ": 100.0,
        "speed": 0.0,
        "time": 0.0
      },
    ]
  }
]