<?xml version='1.0' encoding='UTF-8'?>
<S:Envelope xmlns:S="http://schemas.xmlsoap.org/soap/envelope/">
    <S:Body>
        <ns2:getPointValuesResponse xmlns:ns2="http://ws.bms.swc.lge.com/">
            <return>
                <pointValues>
                    <presentValue>Off</presentValue>
                    <pointPath>point:/ST1/OFa8/LPa232890214279</pointPath>
                    <pointState>NORMAL</pointState>
                    <ddcAlarmStatus>0</ddcAlarmStatus>
                    <ddcCorrectionValue>-9999.9999</ddcCorrectionValue>
                </pointValues>
                <pointValues>
                    <presentValue>Off</presentValue>
                    <pointPath>point:/ST1/OFa8/LPa232890214280</pointPath>
                    <pointState>NORMAL</pointState>
                    <ddcAlarmStatus>0</ddcAlarmStatus>
                    <ddcCorrectionValue>-9999.9999</ddcCorrectionValue>
                </pointValues>
                <pointValues>
                    <presentValue>24.314</presentValue>
                    <pointPath>point:/ST1/OFa8/LPa232890214281</pointPath>
                    <pointState>NORMAL</pointState>
                    <ddcAlarmStatus>0</ddcAlarmStatus>
                    <ddcCorrectionValue>0.0</ddcCorrectionValue>
                </pointValues>
                <pointValues>
                    <presentValue>On</presentValue>
                    <pointPath>point:/ST1/OFa8/LPa232890214282</pointPath>
                    <pointState>NORMAL</pointState>
                    <ddcAlarmStatus>0</ddcAlarmStatus>
                    <ddcCorrectionValue>-9999.9999</ddcCorrectionValue>
                </pointValues>
                <pointValues>
                    <presentValue>Off</presentValue>
                    <pointPath>point:/ST1/OFa8/LPa232890214283</pointPath>
                    <pointState>NORMAL</pointState>
                    <ddcAlarmStatus>0</ddcAlarmStatus>
                    <ddcCorrectionValue>-9999.9999</ddcCorrectionValue>
                </pointValues>
                <pointValues>
                    <presentValue>On</presentValue>
                    <settingValue>On</settingValue>
                    <pointPath>point:/ST1/OFa8/LPa232890214284</pointPath>
                    <pointState>NORMAL</pointState>
                    <ddcAlarmStatus>0</ddcAlarmStatus>
                    <ddcCorrectionValue>-9999.9999</ddcCorrectionValue>
                </pointValues>
                <pointValues>
                    <presentValue>Off</presentValue>
                    <pointPath>point:/ST1/OFa8/LPa232890214285</pointPath>
                    <pointState>NORMAL</pointState>
                    <ddcAlarmStatus>0</ddcAlarmStatus>
                    <ddcCorrectionValue>-9999.9999</ddcCorrectionValue>
                </pointValues>
                <pointValues>
                    <presentValue>On</presentValue>
                    <settingValue>On</settingValue>
                    <pointPath>point:/ST1/OFa8/LPa232890214286</pointPath>
                    <pointState>NORMAL</pointState>
                    <ddcAlarmStatus>0</ddcAlarmStatus>
                    <ddcCorrectionValue>-9999.9999</ddcCorrectionValue>
                </pointValues>
                <pointValues>
                    <presentValue>Off</presentValue>
                    <pointPath>point:/ST1/OFa8/LPa232890214287</pointPath>
                    <pointState>NORMAL</pointState>
                    <ddcAlarmStatus>0</ddcAlarmStatus>
                    <ddcCorrectionValue>-9999.9999</ddcCorrectionValue>
                </pointValues>
                <pointValues>
                    <presentValue>Off</presentValue>
                    <pointPath>point:/ST1/OFa8/LPa232890214288</pointPath>
                    <pointState>NORMAL</pointState>
                    <ddcAlarmStatus>0</ddcAlarmStatus>
                    <ddcCorrectionValue>-9999.9999</ddcCorrectionValue>
                </pointValues>
                <pointValues>
                    <presentValue>Off</presentValue>
                    <pointPath>point:/ST1/OFa8/LPa232890214289</pointPath>
                    <pointState>NORMAL</pointState>
                    <ddcAlarmStatus>0</ddcAlarmStatus>
                    <ddcCorrectionValue>-9999.9999</ddcCorrectionValue>
                </pointValues>
                <pointValues>
                    <presentValue>Off</presentValue>
                    <pointPath>point:/ST1/OFa8/LPa232890214290</pointPath>
                    <pointState>NORMAL</pointState>
                    <ddcAlarmStatus>0</ddcAlarmStatus>
                    <ddcCorrectionValue>-9999.9999</ddcCorrectionValue>
                </pointValues>
                <pointValues>
                    <presentValue>Off</presentValue>
                    <pointPath>point:/ST1/OFa8/LPa232890214291</pointPath>
                    <pointState>NORMAL</pointState>
                    <ddcAlarmStatus>0</ddcAlarmStatus>
                    <ddcCorrectionValue>-9999.9999</ddcCorrectionValue>
                </pointValues>
                <pointValues>
                    <presentValue>49030</presentValue>
                    <pointPath>point:/ST1/OFa8/LPa233586429476</pointPath>
                    <pointState>NORMAL</pointState>
                    <ddcAlarmStatus>0</ddcAlarmStatus>
                    <ddcCorrectionValue>0.0</ddcCorrectionValue>
                </pointValues>
                <pointValues>
                    <presentValue>0</presentValue>
                    <pointPath>point:/ST1/OFa8/LPa233586429477</pointPath>
                    <pointState>NORMAL</pointState>
                    <ddcAlarmStatus>0</ddcAlarmStatus>
                    <ddcCorrectionValue>0.0</ddcCorrectionValue>
                </pointValues>
                <pointValues>
                    <presentValue>1278</presentValue>
                    <pointPath>point:/ST1/OFa8/LPa233586429478</pointPath>
                    <pointState>NORMAL</pointState>
                    <ddcAlarmStatus>0</ddcAlarmStatus>
                    <ddcCorrectionValue>0.0</ddcCorrectionValue>
                </pointValues>
                <pointValues>
                    <presentValue>0</presentValue>
                    <pointPath>point:/ST1/OFa8/LPa233586429479</pointPath>
                    <pointState>NORMAL</pointState>
                    <ddcAlarmStatus>0</ddcAlarmStatus>
                    <ddcCorrectionValue>0.0</ddcCorrectionValue>
                </pointValues>
                <pointValues>
                    <presentValue>22.5</presentValue>
                    <pointPath>point:/ST1/OFa8/LPa233589056311</pointPath>
                    <pointState>NORMAL</pointState>
                    <ddcAlarmStatus>0</ddcAlarmStatus>
                    <ddcCorrectionValue>0.0</ddcCorrectionValue>
                </pointValues>
                <pointValues>
                    <presentValue>0</presentValue>
                    <pointPath>point:/ST1/OFa8/LPa233589056312</pointPath>
                    <pointState>NORMAL</pointState>
                    <ddcAlarmStatus>0</ddcAlarmStatus>
                    <ddcCorrectionValue>0.0</ddcCorrectionValue>
                </pointValues>
                <pointValues>
                    <presentValue>10</presentValue>
                    <pointPath>point:/ST1/OFa8/LPa233589056313</pointPath>
                    <pointState>NORMAL</pointState>
                    <ddcAlarmStatus>0</ddcAlarmStatus>
                    <ddcCorrectionValue>0.0</ddcCorrectionValue>
                </pointValues>
                <pointValues>
                    <presentValue>10.5</presentValue>
                    <pointPath>point:/ST1/OFa8/LPa233589056314</pointPath>
                    <pointState>NORMAL</pointState>
                    <ddcAlarmStatus>0</ddcAlarmStatus>
                    <ddcCorrectionValue>0.0</ddcCorrectionValue>
                </pointValues>
                <pointValues>
                    <presentValue>0</presentValue>
                    <pointPath>point:/ST1/OFa8/LPa233589056315</pointPath>
                    <pointState>NORMAL</pointState>
                    <ddcAlarmStatus>0</ddcAlarmStatus>
                    <ddcCorrectionValue>0.0</ddcCorrectionValue>
                </pointValues>
                <pointValues>
                    <presentValue>3</presentValue>
                    <pointPath>point:/ST1/OFa8/LPa233589056316</pointPath>
                    <pointState>NORMAL</pointState>
                    <ddcAlarmStatus>0</ddcAlarmStatus>
                    <ddcCorrectionValue>0.0</ddcCorrectionValue>
                </pointValues>
                <pointValues>
                    <presentValue>22</presentValue>
                    <settingValue>22</settingValue>
                    <pointPath>point:/ST1/OFa8/LPa233589056317</pointPath>
                    <pointState>NORMAL</pointState>
                    <ddcAlarmStatus>0</ddcAlarmStatus>
                    <ddcCorrectionValue>0.0</ddcCorrectionValue>
                </pointValues>
                <pointValues>
                    <presentValue>4</presentValue>
                    <pointPath>point:/ST1/OFa8/LPa233589056318</pointPath>
                    <pointState>NORMAL</pointState>
                    <ddcAlarmStatus>0</ddcAlarmStatus>
                    <ddcCorrectionValue>0.0</ddcCorrectionValue>
                </pointValues>
                <pointValues>
                    <presentValue>0</presentValue>
                    <pointPath>point:/ST1/OFa8/LPa233589056319</pointPath>
                    <pointState>NORMAL</pointState>
                    <ddcAlarmStatus>0</ddcAlarmStatus>
                    <ddcCorrectionValue>0.0</ddcCorrectionValue>
                </pointValues>
                <pointValues>
                    <presentValue>On</presentValue>
                    <pointPath>point:/ST1/OFa8/LPa233589056320</pointPath>
                    <pointState>NORMAL</pointState>
                    <ddcAlarmStatus>0</ddcAlarmStatus>
                    <ddcCorrectionValue>-9999.9999</ddcCorrectionValue>
                </pointValues>
                <pointValues>
                    <presentValue>On</presentValue>
                    <pointPath>point:/ST1/OFa8/LPa233589056321</pointPath>
                    <pointState>NORMAL</pointState>
                    <ddcAlarmStatus>0</ddcAlarmStatus>
                    <ddcCorrectionValue>-9999.9999</ddcCorrectionValue>
                </pointValues>
                <pointValues>
                    <presentValue>Off</presentValue>
                    <pointPath>point:/ST1/OFa8/LPa233589056322</pointPath>
                    <pointState>NORMAL</pointState>
                    <ddcAlarmStatus>0</ddcAlarmStatus>
                    <ddcCorrectionValue>-9999.9999</ddcCorrectionValue>
                </pointValues>
            </return>
        </ns2:getPointValuesResponse>
    </S:Body>
</S:Envelope>
